cmpfilter/__init__.py
cmpfilter/filters.py
cmpfilter-0.0.1.dist-info/LICENSE
cmpfilter-0.0.1.dist-info/METADATA
cmpfilter-0.0.1.dist-info/WHEEL
cmpfilter-0.0.1.dist-info/top_level.txt
cmpfilter-0.0.1.dist-info/RECORD
