Metadata-Version: 2.1
Name: cmpfilter
Version: 0.0.1
Summary: expand filter() for addressing more complex task.
Home-page: https://github.com/MTamon/CmpFilter.git
Author: Tamon Mikawa
Author-email: mtamon.engineering@gmail.com
License: MIT License
Keywords: expand filter(),Filtering,OverlapedFilter,TiledFilter
Classifier: Development Status :: 4 - Beta
Classifier: License :: OSI Approved :: MIT License
Classifier: Programming Language :: Python
Classifier: Programming Language :: Python :: 3
Classifier: Programming Language :: Python :: 3.9
Classifier: Topic :: Software Development :: Libraries :: Python Modules
License-File: LICENSE
